{
  "1002_NOTES": [
    null,
    null,
    {
      "ID": 2,
      "Link": "https://firebasestorage.googleapis.com/v0/b/houseoftutors-f398e.firebasestorage.app/o/1002_NOTES%2F2?alt=media&token=8893e050-9100-4fc3-a7f2-3c36756b9b13",
      "Name": "G7 -English Paper 1 Pg 5.jpeg",
      "Time": 1741363742286
    },
    {
      "ID": 3,
      "Link": "https://firebasestorage.googleapis.com/v0/b/houseoftutors-f398e.firebasestorage.app/o/1002_NOTES%2F3?alt=media&token=0b31f546-2ea6-4c8a-9545-692e50fdbbbd",
      "Name": "G7 -English Paper 1 Pg 6.jpeg",
      "Time": 1741363844742
    },
    {
      "ID": 4,
      "Link": "https://firebasestorage.googleapis.com/v0/b/houseoftutors-f398e.firebasestorage.app/o/1002_NOTES%2F4?alt=media&token=ad4409f3-1374-4c6b-a4ec-6b3530f563c9",
      "Name": "G7 -English Paper 1 Pg 7.jpeg",
      "Time": 1741363940119
    },
    {
      "ID": 5,
      "Link": "https://firebasestorage.googleapis.com/v0/b/houseoftutors-f398e.firebasestorage.app/o/1002_NOTES%2F5?alt=media&token=764930d4-c6d9-4fcc-9cb4-11eea4f11aa1",
      "Name": "G7 -English Paper 1 Pg 8.jpeg",
      "Time": 1741364003048
    },
    {
      "ID": 6,
      "Link": "https://firebasestorage.googleapis.com/v0/b/houseoftutors-f398e.firebasestorage.app/o/1002_NOTES%2F6?alt=media&token=295c7394-f42b-483f-a967-5e84a12ff875",
      "Name": "G7 -English Paper 1 Pg 9.jpeg",
      "Time": 1741364027551
    },
    {
      "ID": 7,
      "Link": "https://firebasestorage.googleapis.com/v0/b/houseoftutors-f398e.firebasestorage.app/o/1002_NOTES%2F7?alt=media&token=015b92cb-3aa2-4afa-80c6-72022deede36",
      "Name": "G7 -English Paper 1 Pg 10.jpeg",
      "Time": 1741364088230
    },
    {
      "ID": 8,
      "Link": "https://firebasestorage.googleapis.com/v0/b/houseoftutors-f398e.firebasestorage.app/o/1002_NOTES%2F8?alt=media&token=9e641354-36f4-43a2-924a-793ce18042e0",
      "Name": "G7 -English Paper 1 Pg 11.jpeg",
      "Time": 1741364171005
    },
    {
      "ID": 9,
      "Link": "https://firebasestorage.googleapis.com/v0/b/houseoftutors-f398e.firebasestorage.app/o/1002_NOTES%2F9?alt=media&token=2ad346ea-894c-4e51-ab6a-8b173b49a658",
      "Name": "G7 -English Paper 1 Pg 12.jpeg",
      "Time": 1741364217598
    },
    {
      "ID": 10,
      "Link": "https://firebasestorage.googleapis.com/v0/b/houseoftutors-f398e.firebasestorage.app/o/1002_NOTES%2F10?alt=media&token=5127d0c1-0a3b-45f2-b8f5-57ac718659f6",
      "Name": "G7 -English Paper 1 Pg 13.jpeg",
      "Time": 1741364281268
    },
    {
      "ID": 11,
      "Link": "https://firebasestorage.googleapis.com/v0/b/houseoftutors-f398e.firebasestorage.app/o/1002_NOTES%2F11?alt=media&token=ee2b3f2e-85e6-47e1-bc8a-db6c316370d5",
      "Name": "G7 -English Paper 1 Pg 14.jpeg",
      "Time": 1741364311898
    },
    {
      "ID": 12,
      "Link": "https://firebasestorage.googleapis.com/v0/b/houseoftutors-f398e.firebasestorage.app/o/1002_NOTES%2F12?alt=media&token=6b862509-34eb-4fa1-8aa0-7e94f9a43f89",
      "Name": "G7 -English Paper 1 Pg 15.jpeg",
      "Time": 1741364406589
    },
    {
      "ID": 13,
      "Link": "https://firebasestorage.googleapis.com/v0/b/houseoftutors-f398e.firebasestorage.app/o/1002_NOTES%2F13?alt=media&token=6da35a8e-53e0-4ed7-af60-a2a2607a092b",
      "Name": "G7 -English Paper 1 Pg 16.jpeg",
      "Time": 1741364432356
    },
    {
      "ID": 14,
      "Link": "https://firebasestorage.googleapis.com/v0/b/houseoftutors-f398e.firebasestorage.app/o/1002_NOTES%2F14?alt=media&token=db778fd9-4b36-474a-b291-a89bc2751237",
      "Name": "G7 -English Paper 1 Pg 17.jpeg",
      "Time": 1741364483867
    }
  ],
  "1004_NOTES": [
    null,
    null,
    null,
    {
      "ID": 3,
      "Link": "https://firebasestorage.googleapis.com/v0/b/houseoftutors-f398e.firebasestorage.app/o/1004_NOTES%2F3?alt=media&token=4882faf6-f280-4ea1-b43d-0103bc3d07ab",
      "Name": "English Paper 1 Pg 5.jpeg",
      "Time": 1741365109906
    },
    {
      "ID": 4,
      "Link": "https://firebasestorage.googleapis.com/v0/b/houseoftutors-f398e.firebasestorage.app/o/1004_NOTES%2F4?alt=media&token=696a7a27-fa6a-467a-b868-dc659338bce8",
      "Name": "English Paper 1 Pg 6.jpeg",
      "Time": 1741365224992
    },
    {
      "ID": 5,
      "Link": "https://firebasestorage.googleapis.com/v0/b/houseoftutors-f398e.firebasestorage.app/o/1004_NOTES%2F5?alt=media&token=df96ff54-f213-41e8-83b7-f46bb4b960ba",
      "Name": "English Paper 1 Pg 7.jpeg",
      "Time": 1741365335438
    },
    {
      "ID": 6,
      "Link": "https://firebasestorage.googleapis.com/v0/b/houseoftutors-f398e.firebasestorage.app/o/1004_NOTES%2F6?alt=media&token=420b0a27-4f30-425a-93f5-f57ed0594d13",
      "Name": "English Paper 1 Pg 8.jpeg",
      "Time": 1741365357417
    },
    {
      "ID": 7,
      "Link": "https://firebasestorage.googleapis.com/v0/b/houseoftutors-f398e.firebasestorage.app/o/1004_NOTES%2F7?alt=media&token=d9155099-d3ab-4e3a-8f9e-773007baa170",
      "Name": "English Paper 1 Pg 9.jpeg",
      "Time": 1741365532186
    },
    {
      "ID": 8,
      "Link": "https://firebasestorage.googleapis.com/v0/b/houseoftutors-f398e.firebasestorage.app/o/1004_NOTES%2F8?alt=media&token=7141b067-47ab-4358-bbf5-5d014bc439da",
      "Name": "English Paper 1 Pg 10.jpeg",
      "Time": 1741365639303
    },
    {
      "ID": 9,
      "Link": "https://firebasestorage.googleapis.com/v0/b/houseoftutors-f398e.firebasestorage.app/o/1004_NOTES%2F9?alt=media&token=370aacd1-2c87-49b7-99fc-16f2fd277d5a",
      "Name": "English Paper 1 Pg 11.jpeg",
      "Time": 1741365810331
    },
    {
      "ID": 10,
      "Link": "https://firebasestorage.googleapis.com/v0/b/houseoftutors-f398e.firebasestorage.app/o/1004_NOTES%2F10?alt=media&token=367f7d67-b1df-4849-8f69-d098111302c2",
      "Name": "English Paper 1 Pg 12.jpeg",
      "Time": 1741365880433
    },
    {
      "ID": 11,
      "Link": "https://firebasestorage.googleapis.com/v0/b/houseoftutors-f398e.firebasestorage.app/o/1004_NOTES%2F11?alt=media&token=6629cab8-d142-4a6b-aa82-c2fd6dbd37e2",
      "Name": "English Paper 1 Pg 13.jpeg",
      "Time": 1741365908989
    },
    {
      "ID": 12,
      "Link": "https://firebasestorage.googleapis.com/v0/b/houseoftutors-f398e.firebasestorage.app/o/1004_NOTES%2F12?alt=media&token=ee93da3f-2772-4e48-98b5-fcde50a31c9d",
      "Name": "English Paper 1 Pg 14.jpeg",
      "Time": 1741365952548
    },
    {
      "ID": 13,
      "Link": "https://firebasestorage.googleapis.com/v0/b/houseoftutors-f398e.firebasestorage.app/o/1004_NOTES%2F13?alt=media&token=ae9cda36-228c-4ee7-9dfe-6c98a521883f",
      "Name": "English Paper 1 Pg 15.jpeg",
      "Time": 1741365974904
    },
    {
      "ID": 14,
      "Link": "https://firebasestorage.googleapis.com/v0/b/houseoftutors-f398e.firebasestorage.app/o/1004_NOTES%2F14?alt=media&token=39fcda91-3f81-4f8c-aa90-2556eac21fb0",
      "Name": "English Paper 1 Pg 16.jpeg",
      "Time": 1741366017783
    },
    {
      "ID": 15,
      "Link": "https://firebasestorage.googleapis.com/v0/b/houseoftutors-f398e.firebasestorage.app/o/1004_NOTES%2F15?alt=media&token=4821ce95-1f60-4470-b2a0-95e1ce0c447d",
      "Name": "English Paper 1 Pg 17.jpeg",
      "Time": 1741366096097
    }
  ],
  "ADMIN": {
    "ADMIN_1": {
      "EMAIL": "ajtaroo@gmail.com",
      "FULL_NAME": "Ajmal Taroo",
      "PASSWORD": "585054",
      "R_PARTY": "Ajmal Taroo",
      "R_PARTY_TEL": "57882383",
      "TEL": "59185657",
      "VIRTUAL_ROOMS": "1001,1005"
    },
    "ADMIN_2": {
      "EMAIL": "house.of.tutors.48@gmail.com",
      "FULL_NAME": "Shalini Ramful",
      "PASSWORD": "890555",
      "R_PARTY": "ajmal taroo",
      "R_PARTY_TEL": "57882383",
      "TEL": "58505488",
      "VIRTUAL_ROOMS": "1001,1002,1003,1004,1005"
    }
  },
  "CLASSROOMS": {
    "CLASSROOM_1001": {
      "CLASSROOM_ID": 1001,
      "STORAGE_FOLDER": "1001_NOTES",
      "TEACHER_ADDRESS": "House Of Tutors, Mauritius",
      "TEACHER_FULL_NAME": "Shalini Lara Ramful",
      "TEACHER_TEL": "+230 5797 2469",
      "TITLE": "Alishah Hymambaccus's Individual Class",
      "VR_LINK": "https://mindtech.daily.co/HouseOfTutors"
    },
    "CLASSROOM_1002": {
      "CLASSROOM_ID": 1002,
      "STORAGE_FOLDER": "1002_NOTES",
      "TEACHER_ADDRESS": "House Of Tutors, Mauritius",
      "TEACHER_FULL_NAME": "Shalini Lara Ramful",
      "TEACHER_TEL": "+230 5797 2469",
      "TITLE": "Shahbaz Hymambaccus's Individual Class",
      "VR_LINK": "https://mindtech.daily.co/HouseOfTutors"
    },
    "CLASSROOM_1003": {
      "CLASSROOM_ID": 1003,
      "STORAGE_FOLDER": "1003_NOTES",
      "TEACHER_ADDRESS": "House Of Tutors, Mauritius",
      "TEACHER_FULL_NAME": "Shalini Lara Ramful",
      "TEACHER_TEL": "+230 5797 2469",
      "TITLE": "Izel's Individual Class",
      "VR_LINK": "https://mindtech.daily.co/HouseOfTutors"
    },
    "CLASSROOM_1004": {
      "CLASSROOM_ID": 1004,
      "STORAGE_FOLDER": "1004_NOTES",
      "TEACHER_ADDRESS": "House Of Tutors, Mauritius",
      "TEACHER_FULL_NAME": "Shalini Lara Ramful",
      "TEACHER_TEL": "+230 5797 2469",
      "TITLE": "Leah's Individual Class",
      "VR_LINK": "https://mindtech.daily.co/HouseOfTutors"
    },
    "CLASSROOM_1005": {
      "CLASSROOM_ID": 1005,
      "STORAGE_FOLDER": "1005_NOTES",
      "TEACHER_ADDRESS": "House Of Tutors, Mauritius",
      "TEACHER_FULL_NAME": "Adish Dunputh & Shalini ",
      "TEACHER_TEL": "+230 5797 2469",
      "TITLE": "Traditional Massage School",
      "VR_LINK": "https://mindtech.daily.co/HouseOfTutors"
    }
  },
  "NUMBERS": {
    "CURRENT_ID_CLASSROOM": {
      "NUMBER": 1005
    },
    "ID_CLASSROOM_1001_NOTES": {
      "NUMBER": 1
    },
    "ID_CLASSROOM_1002_NOTES": {
      "NUMBER": 14
    },
    "ID_CLASSROOM_1003_NOTES": {
      "NUMBER": 1
    },
    "ID_CLASSROOM_1004_NOTES": {
      "NUMBER": 15
    },
    "ID_CLASSROOM_1005_NOTES": {
      "NUMBER": 1
    },
    "ID_NUMBER": {
      "NUMBER": 100
    },
    "ID_STUDENT": {
      "NUMBER": 7
    }
  },
  "STUDENTS": {
    "STUDENTS_1": {
      "EMAIL": "ajtaroo@gmail.com",
      "FEEDBACK": {
        "FEEDBACK_1741509660138": {
          "DATE": "2025-03-09",
          "FEEDBACK": "very good student"
        },
        "FEEDBACK_1741509774733": {
          "DATE": "2025-03-09",
          "FEEDBACK": "loves shaheena in class"
        }
      },
      "FULL_NAME": "Mohamade Ajmal Taroo",
      "PASSWORD": "585054",
      "R_PARTY": "Ajmal Taroo",
      "R_PARTY_TEL": "57882383",
      "TEL": "59185657",
      "VIRTUAL_ROOMS": "1001,1002,1005"
    },
    "STUDENTS_2": {
      "EMAIL": "alishahhymambaccus@icloud.com",
      "FULL_NAME": "Alishah Hymambaccus",
      "PASSWORD": "777005",
      "R_PARTY": "Dr Outim",
      "R_PARTY_TEL": "58215553",
      "TEL": "52737686",
      "VIRTUAL_ROOMS": "1001"
    },
    "STUDENTS_3": {
      "EMAIL": "shahbazhymambaccus@icloud.com",
      "FULL_NAME": "Shahbaz Hymambaccus",
      "PASSWORD": "597951",
      "R_PARTY": "Dr Outim",
      "R_PARTY_TEL": "58215553",
      "TEL": "55085804",
      "VIRTUAL_ROOMS": "1002"
    },
    "STUDENTS_4": {
      "EMAIL": "izelpww@gmail.com",
      "FULL_NAME": "Izel Poon Wai Wam",
      "PASSWORD": "983398",
      "R_PARTY": "Mr Des ",
      "R_PARTY_TEL": "+44 7940 966984",
      "TEL": "+44 7391 055772",
      "VIRTUAL_ROOMS": "1003"
    },
    "STUDENTS_5": {
      "EMAIL": "leahkpww@gmail.com",
      "FULL_NAME": "Leah Poon Wai Wam",
      "PASSWORD": "961837",
      "R_PARTY": "Mr Des ",
      "R_PARTY_TEL": "+44 7940 966984",
      "TEL": "+44 7379 092857",
      "VIRTUAL_ROOMS": "1004"
    },
    "STUDENTS_6": {
      "EMAIL": "dhunputha@gmail.com",
      "FULL_NAME": "Adish Dunputh",
      "PASSWORD": "981169",
      "R_PARTY": "Mr Dunputh",
      "R_PARTY_TEL": "58013277",
      "TEL": "58013277",
      "VIRTUAL_ROOMS": "1005"
    },
    "def_student": "default"
  },
  "TIME_TABLE": {
    "VALUE": [
      null,
      {
        "00:00 - 00:00": "Leah's Individual Class",
        "08:00 - 09:00": "Leah's Individual Class",
        "08:00 - 12:00": "Izel's Individual Class",
        "10:00 - 11:00": "Shahbaz's Individual Class",
        "14:00 - 15:00": "Alishah's Individual Class"
      },
      {
        "09:00 - 12:00": "Shahbaz's Individual Class"
      },
      null,
      {
        "14:00 - 15:00": "Alishah's Individual Class"
      },
      {
        "00:00 - 00:00": "Alishah's Individual Class"
      }
    ]
  }
}